{
  "project_info": {
    "project_number": "402641775282",
    "firebase_url": "https://cummap-7afee-default-rtdb.europe-west1.firebasedatabase.app",
    "project_id": "cummap-7afee",
    "storage_bucket": "cummap-7afee.firebasestorage.app"
  },
  "client": [
    {
      "client_info": {
        "mobilesdk_app_id": "1:402641775282:android:0b934e37f78f1a5d5937ab",
        "android_client_info": {
          "package_name": "com.cartelnancy.app"
        }
      },
      "oauth_client": [
        {
          "client_id": "402641775282-4gscsht88aek9v7jsfvga58293mi5at1.apps.googleusercontent.com",
          "client_type": 1,
          "android_info": {
            "package_name": "com.cartelnancy.app",
            "certificate_hash": "b93d0dc14308b897bafda30acd92fa908541498c"
          }
        },
        {
          "client_id": "402641775282-flmj306kcpqct1hmrific149uhthiqcq.apps.googleusercontent.com",
          "client_type": 3
        }
      ],
      "api_key": [
        {
          "current_key": "AIzaSyBCM1w1qCKUpXAjXWwHhMAhOIk9y6e1qRM"
        }
      ],
      "services": {
        "appinvite_service": {
          "other_platform_oauth_client": [
            {
              "client_id": "402641775282-flmj306kcpqct1hmrific149uhthiqcq.apps.googleusercontent.com",
              "client_type": 3
            },
            {
              "client_id": "402641775282-bcu1on4ld4bk3609sl9e9rcmvsb23epp.apps.googleusercontent.com",
              "client_type": 2,
              "ios_info": {
                "bundle_id": "com.cartelnancy.app"
              }
            }
          ]
        }
      }
    }
  ],
  "configuration_version": "1"
}